selinon/__init__.py
selinon/builtin_predicate.py
selinon/cache.py
selinon/cache_config.py
selinon/celery.py
selinon/cli.py
selinon/codename.py
selinon/config.py
selinon/data_storage.py
selinon/dispatcher.py
selinon/edge.py
selinon/errors.py
selinon/failure_node.py
selinon/failures.py
selinon/flow.py
selinon/global_config.py
selinon/helpers.py
selinon/leaf_predicate.py
selinon/lock_pool.py
selinon/node.py
selinon/predicate.py
selinon/run.py
selinon/selective.py
selinon/selective_run_function.py
selinon/selinon_task.py
selinon/storage.py
selinon/storage_pool.py
selinon/strategy.py
selinon/system.py
selinon/system_state.py
selinon/task.py
selinon/task_class.py
selinon/task_envelope.py
selinon/trace.py
selinon/user_config.py
selinon/version.py
selinon/caches/__init__.py
selinon/caches/fifo.py
selinon/caches/lifo.py
selinon/caches/lru.py
selinon/caches/mru.py
selinon/caches/rr.py
selinon/executor/__init__.py
selinon/executor/celery_mocks.py
selinon/executor/executor.py
selinon/executor/progress.py
selinon/executor/queue_pool.py
selinon/executor/time_queue.py
selinon/migrations/__init__.py
selinon/migrations/migrator.py
selinon/migrations/tainted_flow_strategy.py
selinon/predicates/__init__.py
selinon/predicates/alwaysFalse.py
selinon/predicates/alwaysTrue.py
selinon/predicates/argsEmpty.py
selinon/predicates/argsFieldBool.py
selinon/predicates/argsFieldContain.py
selinon/predicates/argsFieldDict.py
selinon/predicates/argsFieldEqual.py
selinon/predicates/argsFieldExist.py
selinon/predicates/argsFieldFloat.py
selinon/predicates/argsFieldGreater.py
selinon/predicates/argsFieldGreaterEqual.py
selinon/predicates/argsFieldInt.py
selinon/predicates/argsFieldLenEqual.py
selinon/predicates/argsFieldLenGreater.py
selinon/predicates/argsFieldLenGreaterEqual.py
selinon/predicates/argsFieldLenLess.py
selinon/predicates/argsFieldLenLessEqual.py
selinon/predicates/argsFieldLenNotEqual.py
selinon/predicates/argsFieldLess.py
selinon/predicates/argsFieldLessEqual.py
selinon-1.4.0.dist-info/LICENSE
selinon-1.4.0.dist-info/METADATA
selinon-1.4.0.dist-info/WHEEL
selinon-1.4.0.dist-info/entry_points.txt
selinon-1.4.0.dist-info/top_level.txt
selinon-1.4.0.dist-info/RECORD
