Metadata-Version: 2.1
Name: selinon
Version: 1.4.0
Summary: an advanced dynamic task flow management on top of Celery
Home-page: https://github.com/selinon/selinon
Author: Fridolin Pokorny
Author-email: fridolin.pokorny@gmail.com
Maintainer: Fridolin Pokorny
Maintainer-email: fridolin.pokorny@gmail.com
License: BSD
Keywords: selinon celery yaml flow distributed-computing
Classifier: Development Status :: 4 - Beta
Classifier: Programming Language :: Python :: 3
Classifier: Programming Language :: Python :: 3.9
Classifier: Programming Language :: Python :: 3.10
Classifier: Programming Language :: Python :: 3.11
Classifier: Intended Audience :: Developers
Classifier: License :: OSI Approved :: BSD License
Classifier: Operating System :: OS Independent
Classifier: Topic :: System :: Distributed Computing
Classifier: Programming Language :: Python :: Implementation :: CPython
Classifier: Programming Language :: Python :: Implementation :: PyPy
Requires-Python: >=3.9
License-File: LICENSE
Requires-Dist: click
Requires-Dist: graphviz
Requires-Dist: jsonschema
Requires-Dist: pyyaml
Requires-Dist: rainbow-logging-handler
Provides-Extra: celery
Requires-Dist: celery <6,>=4 ; extra == 'celery'
Provides-Extra: mongodb
Requires-Dist: pymongo >=3.7 ; extra == 'mongodb'
Provides-Extra: postgresql
Requires-Dist: SQLAlchemy ; extra == 'postgresql'
Requires-Dist: SQLAlchemy-Utils ; extra == 'postgresql'
Provides-Extra: redis
Requires-Dist: redis ; extra == 'redis'
Provides-Extra: s3
Requires-Dist: boto3 ; extra == 's3'
Provides-Extra: sentry
Requires-Dist: sentry-sdk ; extra == 'sentry'
